ansible/plugins/inventory/roster.py
ansible_roster-1.1.6.dist-info/LICENSE
ansible_roster-1.1.6.dist-info/METADATA
ansible_roster-1.1.6.dist-info/WHEEL
ansible_roster-1.1.6.dist-info/top_level.txt
ansible_roster-1.1.6.dist-info/zip-safe
ansible_roster-1.1.6.dist-info/RECORD
