Metadata-Version: 2.1
Name: ansible-roster
Version: 1.1.6
Summary: Host based Ansible yaml inventory
Author-email: Julien Lecomte <julien@lecomte.at>
License: MIT
Project-URL: Homepage, https://gitlab.com/jlecomte/ansible/ansible-roster
Project-URL: Documentation, https://jlecomte.gitlab.io/ansible/ansible-roster
Project-URL: Source code, https://gitlab.com/jlecomte/ansible/ansible-roster
Project-URL: Bug tracker, https://gitlab.com/jlecomte/ansible/ansible-roster/-/issues
Classifier: Topic :: System :: Installation/Setup
Classifier: Topic :: System :: Software Distribution
Classifier: Topic :: System :: Systems Administration
Classifier: Intended Audience :: System Administrators
Classifier: Framework :: Ansible
Classifier: License :: OSI Approved :: MIT License
Classifier: Development Status :: 5 - Production/Stable
Classifier: Programming Language :: Python :: 3 :: Only
Classifier: Programming Language :: Python :: 3.7
Classifier: Programming Language :: Python :: 3.8
Classifier: Programming Language :: Python :: 3.9
Requires-Python: >=3.7
License-File: LICENSE
Requires-Dist: cerberus
Requires-Dist: exrex
Requires-Dist: torxtools
